pythonz_symbol-0.1.0.dist-info/METADATA
pythonz_symbol-0.1.0.dist-info/WHEEL
pythonz_symbol/__init__.py
pythonz_symbol-0.1.0.dist-info/RECORD
