Metadata-Version: 2.1
Name: pythonz_symbol
Version: 0.1.0
Summary: symbol implementation of pythonz
Author-Email: Yuichiro Smith <yu-ichiro@s3i7h.com>
License: MIT
Requires-Python: >=3.8
